v2ray/__init__.py
v2ray/base.py
v2ray/protocols_settings.py
v2ray/stream_settings.py
v2ray/v2ray.py
v2raypy-1.1.2.dist-info/licenses/LICENSE
v2raypy-1.1.2.dist-info/METADATA
v2raypy-1.1.2.dist-info/WHEEL
v2raypy-1.1.2.dist-info/top_level.txt
v2raypy-1.1.2.dist-info/RECORD
