Metadata-Version: 2.4
Name: v2raypy
Version: 1.1.2
Summary: A Python library to handle and parse v2ray links
Author-email: Sina Rahimi <sina.rahimi.8125@gmail.com>
License: MIT
Project-URL: Homepage, https://github.com/sina8125/v2raypy
Project-URL: Documentation, https://github.com/sina8125/v2raypy#readme
Project-URL: Repository, https://github.com/sina8125/v2raypy
Project-URL: Bug Tracker, https://github.com/sina8125/v2raypy/issues
Requires-Python: >=3.10
License-File: LICENSE
Dynamic: license-file
